src/__init__.py
src/_backup.py
src/_dbutils.py
src/backuper.py
src/copier.py
src/initializer.py
utils/__init__.py
utils/gitutils.py
utils/gitutils_test.py
utils/manifest.py
utils/manifest_test.py
dodoo_initializer-0.6.1.dist-info/LICENSE
dodoo_initializer-0.6.1.dist-info/METADATA
dodoo_initializer-0.6.1.dist-info/WHEEL
dodoo_initializer-0.6.1.dist-info/entry_points.txt
dodoo_initializer-0.6.1.dist-info/top_level.txt
dodoo_initializer-0.6.1.dist-info/RECORD
