Metadata-Version: 2.1
Name: dodoo-initializer
Version: 0.6.1
Summary: dodoo initializer script
Home-page: http://github.com/xoe-labs/dodoo-initializer
Author: XOE Labs
Author-email: info@xoe.solutions
License: LGPLv3+
Platform: UNKNOWN
Classifier: Development Status :: 4 - Beta
Classifier: Intended Audience :: Developers
Classifier: License :: OSI Approved :: GNU Lesser General Public License v3 or later (LGPLv3+)
Classifier: Programming Language :: Python :: 2.7
Classifier: Programming Language :: Python :: 3.5
Classifier: Programming Language :: Python :: 3.6
Classifier: Programming Language :: Python :: 3.7
Classifier: Framework :: Odoo
Requires-Dist: dodoo (>=2.0.0.rc7)
